{
  "id": "https://nordstemmen.ratsinfomanagement.net/webservice/oparl/v1.1/body/1/meeting/1719",
  "name": "Ortsrat Heyersum (14. Sitzung)",
  "start": "2011-11-17T18:00:00+01:00",
  "location": {
    "id": "https://nordstemmen.ratsinfomanagement.net/webservice/oparl/v1.1/body/1/location/2-8",
    "type": "https://schema.oparl.org/1.1/Location",
    "description": "Altes Schulhaus Heyersum, Martin-Luther-Platz 3, 31171 Nordstemmen, Sitzungszimmer",
    "streetAddress": "Martin-Luther-Platz 3",
    "room": "Altes Schulhaus Heyersum, Sitzungszimmer",
    "postalCode": "31171",
    "subLocality": "Heyersum",
    "locality": "Nordstemmen",
    "created": "2002-08-15T11:37:30+02:00",
    "modified": "2019-10-24T16:49:00+02:00"
  },
  "organization": [
    "https://nordstemmen.ratsinfomanagement.net/webservice/oparl/v1.1/body/1/organization/1-13"
  ],
  "invitation": {
    "id": "https://nordstemmen.ratsinfomanagement.net/webservice/oparl/v1.1/body/1/file/1-7289",
    "type": "https://schema.oparl.org/1.1/File",
    "body": "https://nordstemmen.ratsinfomanagement.net/webservice/oparl/v1.1/body/1",
    "name": "Bekanntmachung (Ortsrat Heyersum)",
    "mimeType": "application/pdf",
    "date": "2011-11-17",
    "accessUrl": "https://nordstemmen.ratsinfomanagement.net/webservice/oparl/v1.1/body/1/files/UGhVM0hpd2NXNFdFcExjZf3mGuEpYeGHltB9brY9-fbpEnovpKyClt2iPXNXU8xq/Bekanntmachung_Ortsrat_Heyersum_17.11.2011.pdf",
    "downloadUrl": "https://nordstemmen.ratsinfomanagement.net/webservice/oparl/v1.1/body/1/files/download/UGhVM0hpd2NXNFdFcExjZf3mGuEpYeGHltB9brY9-fbpEnovpKyClt2iPXNXU8xq/Bekanntmachung_Ortsrat_Heyersum_17.11.2011.pdf",
    "created": "2011-11-08T18:00:52+01:00",
    "modified": "2011-11-08T18:00:52+01:00"
  },
  "resultsProtocol": {
    "id": "https://nordstemmen.ratsinfomanagement.net/webservice/oparl/v1.1/body/1/file/1-7586",
    "type": "https://schema.oparl.org/1.1/File",
    "body": "https://nordstemmen.ratsinfomanagement.net/webservice/oparl/v1.1/body/1",
    "name": "Öffentliche Niederschrift (Ortsrat Heyersum)",
    "mimeType": "application/pdf",
    "date": "2011-11-17",
    "accessUrl": "https://nordstemmen.ratsinfomanagement.net/webservice/oparl/v1.1/body/1/files/UGhVM0hpd2NXNFdFcExjZYv2QwVIvJW-PsqIb9BTHcUAGcPcSY0DPFKSBOE0uZzu/Oeffentliche_Niederschrift_Ortsrat_Heyersum_17.11.2011.pdf",
    "downloadUrl": "https://nordstemmen.ratsinfomanagement.net/webservice/oparl/v1.1/body/1/files/download/UGhVM0hpd2NXNFdFcExjZYv2QwVIvJW-PsqIb9BTHcUAGcPcSY0DPFKSBOE0uZzu/Oeffentliche_Niederschrift_Ortsrat_Heyersum_17.11.2011.pdf",
    "created": "2012-01-12T13:02:15+01:00",
    "modified": "2012-01-12T13:02:15+01:00"
  },
  "agendaItem": [
    {
      "id": "https://nordstemmen.ratsinfomanagement.net/webservice/oparl/v1.1/body/1/agendaitem/7726",
      "type": "https://schema.oparl.org/1.1/AgendaItem",
      "order": 1,
      "name": "- öffentlicher Teil -",
      "created": "2011-11-08T10:52:11+01:00",
      "modified": "2011-12-20T15:19:06+01:00"
    },
    {
      "id": "https://nordstemmen.ratsinfomanagement.net/webservice/oparl/v1.1/body/1/agendaitem/7727",
      "type": "https://schema.oparl.org/1.1/AgendaItem",
      "number": "1",
      "order": 2,
      "name": "Eröffnung der Sitzung\n- Feststellung der ordnungsgemäßen Ladung und der anwesenden Mitglieder\n- Feststellung der Beschlussfähigkeit- ",
      "created": "2011-11-08T10:52:11+01:00",
      "modified": "2011-11-08T10:52:11+01:00"
    },
    {
      "id": "https://nordstemmen.ratsinfomanagement.net/webservice/oparl/v1.1/body/1/agendaitem/7728",
      "type": "https://schema.oparl.org/1.1/AgendaItem",
      "number": "2",
      "order": 3,
      "name": "Verpflichtung und Pflichtenbelehrung durch den bisherigen Ortsbürgermeister",
      "created": "2011-11-08T10:52:11+01:00",
      "modified": "2011-11-08T10:52:11+01:00"
    },
    {
      "id": "https://nordstemmen.ratsinfomanagement.net/webservice/oparl/v1.1/body/1/agendaitem/7736",
      "type": "https://schema.oparl.org/1.1/AgendaItem",
      "number": "3",
      "order": 4,
      "name": "Bekanntgabe der Bildung von Fraktionen und Gruppen",
      "created": "2011-11-08T10:53:37+01:00",
      "modified": "2011-11-08T10:53:37+01:00"
    },
    {
      "id": "https://nordstemmen.ratsinfomanagement.net/webservice/oparl/v1.1/body/1/agendaitem/7737",
      "type": "https://schema.oparl.org/1.1/AgendaItem",
      "number": "4",
      "order": 5,
      "name": "Wahl der Ortsbürgermeisterin / des Ortsbürgermeisters",
      "created": "2011-11-08T10:54:02+01:00",
      "modified": "2011-11-08T10:54:02+01:00"
    },
    {
      "id": "https://nordstemmen.ratsinfomanagement.net/webservice/oparl/v1.1/body/1/agendaitem/7738",
      "type": "https://schema.oparl.org/1.1/AgendaItem",
      "number": "5",
      "order": 6,
      "name": "Feststellung der Tagesordnung",
      "created": "2011-11-08T10:54:25+01:00",
      "modified": "2011-11-08T10:54:25+01:00"
    },
    {
      "id": "https://nordstemmen.ratsinfomanagement.net/webservice/oparl/v1.1/body/1/agendaitem/7739",
      "type": "https://schema.oparl.org/1.1/AgendaItem",
      "number": "6",
      "order": 7,
      "name": "Wahl einer stellvertretenden Ortsbürgermeisterin / eines stellvertretenden Ortsbürgermeisters",
      "created": "2011-11-08T10:54:59+01:00",
      "modified": "2011-11-08T10:54:59+01:00"
    },
    {
      "id": "https://nordstemmen.ratsinfomanagement.net/webservice/oparl/v1.1/body/1/agendaitem/7740",
      "type": "https://schema.oparl.org/1.1/AgendaItem",
      "number": "7",
      "order": 8,
      "name": "Verabschiedung ausgeschiedener Ortsratsmitglieder",
      "created": "2011-11-08T10:56:03+01:00",
      "modified": "2011-11-08T10:56:03+01:00"
    },
    {
      "id": "https://nordstemmen.ratsinfomanagement.net/webservice/oparl/v1.1/body/1/agendaitem/7729",
      "type": "https://schema.oparl.org/1.1/AgendaItem",
      "number": "8",
      "order": 9,
      "name": "Einwohnerfragestunde",
      "created": "2011-11-08T10:52:11+01:00",
      "modified": "2011-11-08T10:52:11+01:00"
    },
    {
      "id": "https://nordstemmen.ratsinfomanagement.net/webservice/oparl/v1.1/body/1/agendaitem/7741",
      "type": "https://schema.oparl.org/1.1/AgendaItem",
      "number": "9",
      "order": 10,
      "name": "Benennung einer Vertreterin / eines Vertreters einschließlich Stellvertretung aus dem Ortsrat für den Kindertagesstättenausschuss des Kindergartens in der Ortschaft Heyersum",
      "created": "2011-11-08T10:58:49+01:00",
      "modified": "2011-11-08T10:58:49+01:00"
    },
    {
      "id": "https://nordstemmen.ratsinfomanagement.net/webservice/oparl/v1.1/body/1/agendaitem/7742",
      "type": "https://schema.oparl.org/1.1/AgendaItem",
      "number": "10",
      "order": 11,
      "name": "Durchführung der Seniorenadventsfeier",
      "created": "2011-11-08T10:59:04+01:00",
      "modified": "2011-11-08T10:59:04+01:00"
    },
    {
      "id": "https://nordstemmen.ratsinfomanagement.net/webservice/oparl/v1.1/body/1/agendaitem/7730",
      "type": "https://schema.oparl.org/1.1/AgendaItem",
      "number": "11",
      "order": 12,
      "name": "Mitteilungen des Bürgermeisters",
      "created": "2011-11-08T10:52:11+01:00",
      "modified": "2011-11-08T10:52:11+01:00"
    },
    {
      "id": "https://nordstemmen.ratsinfomanagement.net/webservice/oparl/v1.1/body/1/agendaitem/7731",
      "type": "https://schema.oparl.org/1.1/AgendaItem",
      "number": "12",
      "order": 13,
      "name": "Mitteilungen der Ortsbürgermeisterin / des Ortsbürgermeisters",
      "created": "2011-11-08T10:52:11+01:00",
      "modified": "2011-11-08T10:52:11+01:00"
    },
    {
      "id": "https://nordstemmen.ratsinfomanagement.net/webservice/oparl/v1.1/body/1/agendaitem/7732",
      "type": "https://schema.oparl.org/1.1/AgendaItem",
      "number": "13",
      "order": 15,
      "name": "Behandlung von schriftlichen Anfragen und Anträgen",
      "created": "2011-11-08T10:52:11+01:00",
      "modified": "2011-11-08T10:52:11+01:00"
    },
    {
      "id": "https://nordstemmen.ratsinfomanagement.net/webservice/oparl/v1.1/body/1/agendaitem/7734",
      "type": "https://schema.oparl.org/1.1/AgendaItem",
      "number": "14",
      "order": 16,
      "name": "Anregungen",
      "created": "2011-11-08T10:52:11+01:00",
      "modified": "2011-11-08T10:52:11+01:00"
    }
  ]
}