{
  "id": "https://nordstemmen.ratsinfomanagement.net/webservice/oparl/v1.1/body/1/paper/527",
  "reference": "DS 53/2010",
  "name": "20. Änderung des Flächennutzungsplanes (Obere Wanne) und Bebauungsplan Nr. 0208 \"Obere Wanne - Bioenergienutzung\", Ortschaft Adensen",
  "paperType": "Beschlussvorlage",
  "date": "2010-10-25",
  "mainFile": {
    "id": "https://nordstemmen.ratsinfomanagement.net/webservice/oparl/v1.1/body/1/file/1-5771",
    "type": "https://schema.oparl.org/1.1/File",
    "body": "https://nordstemmen.ratsinfomanagement.net/webservice/oparl/v1.1/body/1",
    "name": "Beschlussvorlage (20. Änderung des Flächennutzungsplanes (Obere Wanne) und Bebauungsplan Nr. 0208 \"Obere Wanne - Bioenergienutzung\", Ortschaft Adensen)",
    "mimeType": "application/pdf",
    "date": "2010-10-25",
    "accessUrl": "https://nordstemmen.ratsinfomanagement.net/webservice/oparl/v1.1/body/1/files/UGhVM0hpd2NXNFdFcExjZSjAxSIdOzReYFl0VevjfJD--3eDIm8bjFuBnp4jipcT/Beschlussvorlage_DS_53-2010.pdf",
    "downloadUrl": "https://nordstemmen.ratsinfomanagement.net/webservice/oparl/v1.1/body/1/files/download/UGhVM0hpd2NXNFdFcExjZSjAxSIdOzReYFl0VevjfJD--3eDIm8bjFuBnp4jipcT/Beschlussvorlage_DS_53-2010.pdf",
    "created": "2010-10-14T13:09:01+02:00",
    "modified": "2010-10-14T13:09:01+02:00"
  },
  "consultation": [
    {
      "id": "https://nordstemmen.ratsinfomanagement.net/webservice/oparl/v1.1/body/1/consultation/1375",
      "type": "https://schema.oparl.org/1.1/Consultation",
      "agendaItem": "https://nordstemmen.ratsinfomanagement.net/webservice/oparl/v1.1/body/1/agendaitem/6517",
      "meeting": "https://nordstemmen.ratsinfomanagement.net/webservice/oparl/v1.1/body/1/meeting/1529",
      "organization": [
        "https://nordstemmen.ratsinfomanagement.net/webservice/oparl/v1.1/body/1/organization/1-11"
      ],
      "created": "2010-10-06T11:10:44+02:00",
      "modified": "2010-10-06T11:10:44+02:00"
    }
  ]
}