{
  "id": "https://nordstemmen.ratsinfomanagement.net/webservice/oparl/v1.1/body/1/meeting/4997",
  "name": "Ortsrat Heyersum (3. Sitzung)",
  "start": "2022-05-12T18:00:00+02:00",
  "location": {
    "id": "https://nordstemmen.ratsinfomanagement.net/webservice/oparl/v1.1/body/1/location/2-8",
    "type": "https://schema.oparl.org/1.1/Location",
    "description": "Altes Schulhaus Heyersum, Martin-Luther-Platz 3, 31171 Nordstemmen, Sitzungszimmer",
    "streetAddress": "Martin-Luther-Platz 3",
    "room": "Altes Schulhaus Heyersum, Sitzungszimmer",
    "postalCode": "31171",
    "subLocality": "Heyersum",
    "locality": "Nordstemmen",
    "created": "2002-08-15T11:37:30+02:00",
    "modified": "2019-10-24T16:49:00+02:00"
  },
  "organization": [
    "https://nordstemmen.ratsinfomanagement.net/webservice/oparl/v1.1/body/1/organization/1-13"
  ],
  "invitation": {
    "id": "https://nordstemmen.ratsinfomanagement.net/webservice/oparl/v1.1/body/1/file/1-33944",
    "type": "https://schema.oparl.org/1.1/File",
    "body": "https://nordstemmen.ratsinfomanagement.net/webservice/oparl/v1.1/body/1",
    "name": "Bekanntmachung (Ortsrat Heyersum)",
    "mimeType": "application/pdf",
    "date": "2022-05-12",
    "accessUrl": "https://nordstemmen.ratsinfomanagement.net/webservice/oparl/v1.1/body/1/files/UGhVM0hpd2NXNFdFcExjZTc78llfBQLbk8X-9LDjbcpJyQ6jr8SzoIfkyuMq4mdu/Bekanntmachung_Ortsrat_Heyersum_12.05.2022.pdf",
    "downloadUrl": "https://nordstemmen.ratsinfomanagement.net/webservice/oparl/v1.1/body/1/files/download/UGhVM0hpd2NXNFdFcExjZTc78llfBQLbk8X-9LDjbcpJyQ6jr8SzoIfkyuMq4mdu/Bekanntmachung_Ortsrat_Heyersum_12.05.2022.pdf",
    "created": "2022-04-27T11:52:34+02:00",
    "modified": "2022-04-27T11:52:34+02:00"
  },
  "resultsProtocol": {
    "id": "https://nordstemmen.ratsinfomanagement.net/webservice/oparl/v1.1/body/1/file/1-34174",
    "type": "https://schema.oparl.org/1.1/File",
    "body": "https://nordstemmen.ratsinfomanagement.net/webservice/oparl/v1.1/body/1",
    "name": "Öffentliche Niederschrift (Ortsrat Heyersum)",
    "mimeType": "application/pdf",
    "date": "2022-05-12",
    "accessUrl": "https://nordstemmen.ratsinfomanagement.net/webservice/oparl/v1.1/body/1/files/UGhVM0hpd2NXNFdFcExjZTV3YD3XKMcsYJ135W_Stdd0HkbJwT41JAXPkImNmpzN/Oeffentliche_Niederschrift_Ortsrat_Heyersum_12.05.2022.pdf",
    "downloadUrl": "https://nordstemmen.ratsinfomanagement.net/webservice/oparl/v1.1/body/1/files/download/UGhVM0hpd2NXNFdFcExjZTV3YD3XKMcsYJ135W_Stdd0HkbJwT41JAXPkImNmpzN/Oeffentliche_Niederschrift_Ortsrat_Heyersum_12.05.2022.pdf",
    "created": "2022-05-25T19:00:19+02:00",
    "modified": "2022-05-25T19:00:19+02:00"
  },
  "agendaItem": [
    {
      "id": "https://nordstemmen.ratsinfomanagement.net/webservice/oparl/v1.1/body/1/agendaitem/19860",
      "type": "https://schema.oparl.org/1.1/AgendaItem",
      "order": 1,
      "name": "- öffentlicher Teil -",
      "created": "2022-03-10T17:48:57+01:00",
      "modified": "2022-03-10T17:48:57+01:00"
    },
    {
      "id": "https://nordstemmen.ratsinfomanagement.net/webservice/oparl/v1.1/body/1/agendaitem/19861",
      "type": "https://schema.oparl.org/1.1/AgendaItem",
      "number": "1",
      "order": 2,
      "name": "Eröffnung der Sitzung\n- Feststellung der ordnungsgemäßen Ladung und der anwesenden Mitglieder\n- Feststellung der Beschlussfähigkeit\n- Beschlussfassung über Anträge zur Tagesordnung\n- Feststellung der Tagesordnung",
      "created": "2022-03-10T17:48:57+01:00",
      "modified": "2022-03-10T17:48:57+01:00"
    },
    {
      "id": "https://nordstemmen.ratsinfomanagement.net/webservice/oparl/v1.1/body/1/agendaitem/19862",
      "type": "https://schema.oparl.org/1.1/AgendaItem",
      "number": "2",
      "order": 3,
      "name": "Genehmigung des Protokolls der Sitzung vom 17. Februar 2022",
      "created": "2022-03-10T17:48:57+01:00",
      "modified": "2022-03-10T17:48:57+01:00"
    },
    {
      "id": "https://nordstemmen.ratsinfomanagement.net/webservice/oparl/v1.1/body/1/agendaitem/19864",
      "type": "https://schema.oparl.org/1.1/AgendaItem",
      "number": "3",
      "order": 4,
      "name": "Bericht bzw. Mitteilungen der Bürgermeisterin",
      "auxiliaryFile": [
        {
          "id": "https://nordstemmen.ratsinfomanagement.net/webservice/oparl/v1.1/body/1/file/2-5594",
          "type": "https://schema.oparl.org/1.1/File",
          "body": "https://nordstemmen.ratsinfomanagement.net/webservice/oparl/v1.1/body/1",
          "name": "Infotext (Anlage 1)",
          "mimeType": "application/pdf",
          "date": "2022-05-12",
          "accessUrl": "https://nordstemmen.ratsinfomanagement.net/webservice/oparl/v1.1/body/1/files/UGhVM0hpd2NXNFdFcExjZUzAeaKfIcPPb8dOL9QaY0Wu_I8TFIR6drbEsm4O9xNA/Anlage_1.pdf",
          "downloadUrl": "https://nordstemmen.ratsinfomanagement.net/webservice/oparl/v1.1/body/1/files/download/UGhVM0hpd2NXNFdFcExjZUzAeaKfIcPPb8dOL9QaY0Wu_I8TFIR6drbEsm4O9xNA/Anlage_1.pdf",
          "created": "2022-05-25T19:00:19+02:00",
          "modified": "2022-05-25T19:00:19+02:00"
        }
      ],
      "created": "2022-03-10T17:48:57+01:00",
      "modified": "2022-03-10T17:48:57+01:00"
    },
    {
      "id": "https://nordstemmen.ratsinfomanagement.net/webservice/oparl/v1.1/body/1/agendaitem/19865",
      "type": "https://schema.oparl.org/1.1/AgendaItem",
      "number": "4",
      "order": 5,
      "name": "Bericht bzw. Mitteilungen des Ortsbürgermeisters",
      "auxiliaryFile": [
        {
          "id": "https://nordstemmen.ratsinfomanagement.net/webservice/oparl/v1.1/body/1/file/2-5595",
          "type": "https://schema.oparl.org/1.1/File",
          "body": "https://nordstemmen.ratsinfomanagement.net/webservice/oparl/v1.1/body/1",
          "name": "Infotext (Anlage 2)",
          "mimeType": "application/pdf",
          "date": "2022-05-12",
          "accessUrl": "https://nordstemmen.ratsinfomanagement.net/webservice/oparl/v1.1/body/1/files/UGhVM0hpd2NXNFdFcExjZZ5ivgQGHyy9L9VQOWqD4Gj6488er826UVKF9618oum6/Anlage_2.pdf",
          "downloadUrl": "https://nordstemmen.ratsinfomanagement.net/webservice/oparl/v1.1/body/1/files/download/UGhVM0hpd2NXNFdFcExjZZ5ivgQGHyy9L9VQOWqD4Gj6488er826UVKF9618oum6/Anlage_2.pdf",
          "created": "2022-05-25T19:00:19+02:00",
          "modified": "2022-05-25T19:00:19+02:00"
        }
      ],
      "created": "2022-03-10T17:48:57+01:00",
      "modified": "2022-03-10T17:48:57+01:00"
    },
    {
      "id": "https://nordstemmen.ratsinfomanagement.net/webservice/oparl/v1.1/body/1/agendaitem/19863",
      "type": "https://schema.oparl.org/1.1/AgendaItem",
      "number": "5",
      "order": 6,
      "name": "Einwohnerfragestunde",
      "created": "2022-03-10T17:48:57+01:00",
      "modified": "2022-04-25T13:20:37+02:00"
    },
    {
      "id": "https://nordstemmen.ratsinfomanagement.net/webservice/oparl/v1.1/body/1/agendaitem/19975",
      "type": "https://schema.oparl.org/1.1/AgendaItem",
      "number": "6",
      "order": 7,
      "name": "Umsetzung einer Straßeneinengung (Pflanzenbeet) in der Stellmacherstraße\n– erneute Beratung und Beschlussfassung",
      "created": "2022-04-25T13:21:01+02:00",
      "modified": "2022-04-25T13:21:01+02:00"
    },
    {
      "id": "https://nordstemmen.ratsinfomanagement.net/webservice/oparl/v1.1/body/1/agendaitem/19866",
      "type": "https://schema.oparl.org/1.1/AgendaItem",
      "number": "7",
      "order": 8,
      "name": "Anträge und Anfragen",
      "created": "2022-03-10T17:48:57+01:00",
      "modified": "2022-03-10T17:48:57+01:00"
    }
  ]
}