{
  "id": "https://nordstemmen.ratsinfomanagement.net/webservice/oparl/v1.1/body/1/paper/5103",
  "reference": "DS 10/2022",
  "name": "Angebot zum Erwerb einer Grünanlage",
  "paperType": "Beschlussvorlage",
  "date": "2022-03-29",
  "mainFile": {
    "id": "https://nordstemmen.ratsinfomanagement.net/webservice/oparl/v1.1/body/1/file/1-33248",
    "type": "https://schema.oparl.org/1.1/File",
    "body": "https://nordstemmen.ratsinfomanagement.net/webservice/oparl/v1.1/body/1",
    "name": "Beschlussvorlage (Angebot zum Erwerb einer Grünanlage)",
    "mimeType": "application/pdf",
    "date": "2022-03-29",
    "accessUrl": "https://nordstemmen.ratsinfomanagement.net/webservice/oparl/v1.1/body/1/files/UGhVM0hpd2NXNFdFcExjZQ2hWnhm6qeaLKwXxDjhDxjfaZKTdxi_lNDF_pzz6zLI/Beschlussvorlage_DS_10-2022.pdf",
    "downloadUrl": "https://nordstemmen.ratsinfomanagement.net/webservice/oparl/v1.1/body/1/files/download/UGhVM0hpd2NXNFdFcExjZQ2hWnhm6qeaLKwXxDjhDxjfaZKTdxi_lNDF_pzz6zLI/Beschlussvorlage_DS_10-2022.pdf",
    "created": "2022-03-10T14:39:14+01:00",
    "modified": "2022-07-01T13:00:29+02:00"
  },
  "auxiliaryFile": [
    {
      "id": "https://nordstemmen.ratsinfomanagement.net/webservice/oparl/v1.1/body/1/file/2-5546",
      "type": "https://schema.oparl.org/1.1/File",
      "body": "https://nordstemmen.ratsinfomanagement.net/webservice/oparl/v1.1/body/1",
      "name": "Beschlussvorlage (Anlage)",
      "mimeType": "application/pdf",
      "date": "2022-03-29",
      "accessUrl": "https://nordstemmen.ratsinfomanagement.net/webservice/oparl/v1.1/body/1/files/UGhVM0hpd2NXNFdFcExjZVMnkGlj9Yp-P0fzmbnS8oXR-XBXjPL327WByP0hScIN/Anlage.pdf",
      "downloadUrl": "https://nordstemmen.ratsinfomanagement.net/webservice/oparl/v1.1/body/1/files/download/UGhVM0hpd2NXNFdFcExjZVMnkGlj9Yp-P0fzmbnS8oXR-XBXjPL327WByP0hScIN/Anlage.pdf",
      "created": "2022-03-10T14:39:14+01:00",
      "modified": "2022-03-10T14:39:14+01:00"
    }
  ],
  "consultation": [
    {
      "id": "https://nordstemmen.ratsinfomanagement.net/webservice/oparl/v1.1/body/1/consultation/7292",
      "type": "https://schema.oparl.org/1.1/Consultation",
      "agendaItem": "https://nordstemmen.ratsinfomanagement.net/webservice/oparl/v1.1/body/1/agendaitem/19800",
      "meeting": "https://nordstemmen.ratsinfomanagement.net/webservice/oparl/v1.1/body/1/meeting/4986",
      "organization": [
        "https://nordstemmen.ratsinfomanagement.net/webservice/oparl/v1.1/body/1/organization/1-29"
      ],
      "created": "2022-02-07T15:24:57+01:00",
      "modified": "2022-02-07T15:24:57+01:00"
    },
    {
      "id": "https://nordstemmen.ratsinfomanagement.net/webservice/oparl/v1.1/body/1/consultation/7294",
      "type": "https://schema.oparl.org/1.1/Consultation",
      "agendaItem": "https://nordstemmen.ratsinfomanagement.net/webservice/oparl/v1.1/body/1/agendaitem/19748",
      "meeting": "https://nordstemmen.ratsinfomanagement.net/webservice/oparl/v1.1/body/1/meeting/5012",
      "organization": [
        "https://nordstemmen.ratsinfomanagement.net/webservice/oparl/v1.1/body/1/organization/1-1"
      ],
      "created": "2022-02-07T15:25:15+01:00",
      "modified": "2022-02-07T15:25:15+01:00"
    }
  ]
}