{
  "id": "https://nordstemmen.ratsinfomanagement.net/webservice/oparl/v1.1/body/1/meeting/5766",
  "name": "Fachausschuss Schule, Jugend, Soziales und Kultur (18. Sitzung)",
  "start": "2025-08-28T18:00:00+02:00",
  "location": {
    "id": "https://nordstemmen.ratsinfomanagement.net/webservice/oparl/v1.1/body/1/location/2-1",
    "type": "https://schema.oparl.org/1.1/Location",
    "description": "Rathaus, Rathausstraße 3, 31171 Nordstemmen, Sitzungszimmer",
    "streetAddress": "Rathausstraße 3",
    "room": "Rathaus, Sitzungszimmer",
    "postalCode": "31171",
    "locality": "Nordstemmen",
    "created": "2002-08-14T09:09:58+02:00",
    "modified": "2017-09-14T11:14:32+02:00"
  },
  "organization": [
    "https://nordstemmen.ratsinfomanagement.net/webservice/oparl/v1.1/body/1/organization/1-41"
  ],
  "agendaItem": [
    {
      "id": "https://nordstemmen.ratsinfomanagement.net/webservice/oparl/v1.1/body/1/agendaitem/23749",
      "type": "https://schema.oparl.org/1.1/AgendaItem",
      "number": "1",
      "order": 1,
      "name": "- öffentlicher Teil -",
      "created": "2025-08-18T11:17:46+02:00",
      "modified": "2025-08-18T11:17:46+02:00"
    },
    {
      "id": "https://nordstemmen.ratsinfomanagement.net/webservice/oparl/v1.1/body/1/agendaitem/23750",
      "type": "https://schema.oparl.org/1.1/AgendaItem",
      "number": "1",
      "order": 2,
      "name": "Eröffnung der Sitzung\n- Feststellung der ordnungsgemäßen Ladung und der anwesenden Mitglieder\n- Feststellung der Beschlussfähigkeit\n- Beschlussfassung über Anträge zur Tagesordnung\n- Feststellung der Tagesordnung",
      "created": "2025-08-18T11:17:46+02:00",
      "modified": "2025-08-18T11:17:46+02:00"
    },
    {
      "id": "https://nordstemmen.ratsinfomanagement.net/webservice/oparl/v1.1/body/1/agendaitem/23752",
      "type": "https://schema.oparl.org/1.1/AgendaItem",
      "number": "2",
      "order": 3,
      "name": "Anfragen und Anregungen",
      "created": "2025-08-18T11:17:46+02:00",
      "modified": "2025-08-18T11:17:46+02:00"
    },
    {
      "id": "https://nordstemmen.ratsinfomanagement.net/webservice/oparl/v1.1/body/1/agendaitem/23753",
      "type": "https://schema.oparl.org/1.1/AgendaItem",
      "number": "3",
      "order": 4,
      "name": "Einwohner*innen Fragestunde",
      "created": "2025-08-18T11:17:46+02:00",
      "modified": "2025-08-18T11:17:46+02:00"
    },
    {
      "id": "https://nordstemmen.ratsinfomanagement.net/webservice/oparl/v1.1/body/1/agendaitem/23754",
      "type": "https://schema.oparl.org/1.1/AgendaItem",
      "number": "4",
      "order": 5,
      "name": "Ganztagsgrundschule Asternschule, Vorstellung des überarbeiteten Raumprogramms und Erläuterung der Vorzugsvariante",
      "consultation": "https://nordstemmen.ratsinfomanagement.net/webservice/oparl/v1.1/body/1/consultation/8485",
      "created": "2025-08-18T11:17:46+02:00",
      "modified": "2025-08-18T11:17:46+02:00"
    },
    {
      "id": "https://nordstemmen.ratsinfomanagement.net/webservice/oparl/v1.1/body/1/agendaitem/23755",
      "type": "https://schema.oparl.org/1.1/AgendaItem",
      "number": "5",
      "order": 6,
      "name": "Mitteilungen der Verwaltung",
      "created": "2025-08-18T11:17:46+02:00",
      "modified": "2025-08-18T11:17:46+02:00"
    }
  ]
}