{
  "id": "https://nordstemmen.ratsinfomanagement.net/webservice/oparl/v1.1/body/1/paper/4710",
  "reference": "DS 29/2019",
  "name": "Abberufung der ehrenamtlichen Gleichstellungsbeauftragten",
  "paperType": "Beschlussvorlage",
  "date": "2019-03-26",
  "mainFile": {
    "id": "https://nordstemmen.ratsinfomanagement.net/webservice/oparl/v1.1/body/1/file/1-26464",
    "type": "https://schema.oparl.org/1.1/File",
    "body": "https://nordstemmen.ratsinfomanagement.net/webservice/oparl/v1.1/body/1",
    "name": "Beschlussvorlage (Abberufung der ehrenamtlichen Gleichstellungsbeauftragten)",
    "mimeType": "application/pdf",
    "date": "2019-03-26",
    "accessUrl": "https://nordstemmen.ratsinfomanagement.net/webservice/oparl/v1.1/body/1/files/UGhVM0hpd2NXNFdFcExjZWcDIhtrw-AMCOgiEqBM76OZfpo5SmUXHxVyAE7NfaLa/Beschlussvorlage_DS_29-2019.pdf",
    "downloadUrl": "https://nordstemmen.ratsinfomanagement.net/webservice/oparl/v1.1/body/1/files/download/UGhVM0hpd2NXNFdFcExjZWcDIhtrw-AMCOgiEqBM76OZfpo5SmUXHxVyAE7NfaLa/Beschlussvorlage_DS_29-2019.pdf",
    "created": "2019-02-22T13:01:21+01:00",
    "modified": "2019-04-08T13:02:00+02:00"
  },
  "consultation": [
    {
      "id": "https://nordstemmen.ratsinfomanagement.net/webservice/oparl/v1.1/body/1/consultation/6501",
      "type": "https://schema.oparl.org/1.1/Consultation",
      "agendaItem": "https://nordstemmen.ratsinfomanagement.net/webservice/oparl/v1.1/body/1/agendaitem/16355",
      "meeting": "https://nordstemmen.ratsinfomanagement.net/webservice/oparl/v1.1/body/1/meeting/4234",
      "organization": [
        "https://nordstemmen.ratsinfomanagement.net/webservice/oparl/v1.1/body/1/organization/1-1"
      ],
      "created": "2019-02-22T11:53:55+01:00",
      "modified": "2019-02-22T11:53:55+01:00"
    }
  ]
}