{
  "id": "https://nordstemmen.ratsinfomanagement.net/webservice/oparl/v1.1/body/1/meeting/2790",
  "name": "Ortsrat Rössing (37. Sitzung)",
  "start": "2016-11-15T18:00:00+01:00",
  "location": {
    "id": "https://nordstemmen.ratsinfomanagement.net/webservice/oparl/v1.1/body/1/location/2-26",
    "type": "https://schema.oparl.org/1.1/Location",
    "description": "Gaststätte \"Zum Dorfbrunnen\", Loderwinkel 2 a, 31171 Nordstemmen, Clubraum",
    "streetAddress": "Loderwinkel 2 a",
    "room": "Gaststätte \"Zum Dorfbrunnen\", Clubraum",
    "postalCode": "31171",
    "subLocality": "Rössing",
    "locality": "Nordstemmen",
    "created": "2014-10-09T10:17:13+02:00",
    "modified": "2017-09-12T17:09:54+02:00"
  },
  "organization": [
    "https://nordstemmen.ratsinfomanagement.net/webservice/oparl/v1.1/body/1/organization/1-15"
  ],
  "invitation": {
    "id": "https://nordstemmen.ratsinfomanagement.net/webservice/oparl/v1.1/body/1/file/1-17411",
    "type": "https://schema.oparl.org/1.1/File",
    "body": "https://nordstemmen.ratsinfomanagement.net/webservice/oparl/v1.1/body/1",
    "name": "Bekanntmachung (Ortsrat Rössing)",
    "mimeType": "application/pdf",
    "date": "2016-11-15",
    "accessUrl": "https://nordstemmen.ratsinfomanagement.net/webservice/oparl/v1.1/body/1/files/UGhVM0hpd2NXNFdFcExjZekZ4eZynRA60DO8uj0ZikhRpooYE-UYV4t5qukcsVRI/Bekanntmachung_Ortsrat_Roessing_15.11.2016.pdf",
    "downloadUrl": "https://nordstemmen.ratsinfomanagement.net/webservice/oparl/v1.1/body/1/files/download/UGhVM0hpd2NXNFdFcExjZekZ4eZynRA60DO8uj0ZikhRpooYE-UYV4t5qukcsVRI/Bekanntmachung_Ortsrat_Roessing_15.11.2016.pdf",
    "created": "2016-11-04T13:02:04+01:00",
    "modified": "2016-11-04T13:02:04+01:00"
  },
  "resultsProtocol": {
    "id": "https://nordstemmen.ratsinfomanagement.net/webservice/oparl/v1.1/body/1/file/1-17947",
    "type": "https://schema.oparl.org/1.1/File",
    "body": "https://nordstemmen.ratsinfomanagement.net/webservice/oparl/v1.1/body/1",
    "name": "Öffentliche Niederschrift (Ortsrat Rössing)",
    "mimeType": "application/pdf",
    "date": "2016-11-15",
    "accessUrl": "https://nordstemmen.ratsinfomanagement.net/webservice/oparl/v1.1/body/1/files/UGhVM0hpd2NXNFdFcExjZTs2tBgo-j-qxt6646TAgSRCMHjJNNg1l3zlcGVhMC4-/Oeffentliche_Niederschrift_Ortsrat_Roessing_15.11.2016.pdf",
    "downloadUrl": "https://nordstemmen.ratsinfomanagement.net/webservice/oparl/v1.1/body/1/files/download/UGhVM0hpd2NXNFdFcExjZTs2tBgo-j-qxt6646TAgSRCMHjJNNg1l3zlcGVhMC4-/Oeffentliche_Niederschrift_Ortsrat_Roessing_15.11.2016.pdf",
    "created": "2016-12-16T13:01:45+01:00",
    "modified": "2016-12-16T13:01:45+01:00"
  },
  "agendaItem": [
    {
      "id": "https://nordstemmen.ratsinfomanagement.net/webservice/oparl/v1.1/body/1/agendaitem/13453",
      "type": "https://schema.oparl.org/1.1/AgendaItem",
      "order": 1,
      "name": "- öffentlicher Teil -",
      "created": "2016-11-03T14:14:26+01:00",
      "modified": "2016-11-03T14:14:26+01:00"
    },
    {
      "id": "https://nordstemmen.ratsinfomanagement.net/webservice/oparl/v1.1/body/1/agendaitem/13454",
      "type": "https://schema.oparl.org/1.1/AgendaItem",
      "number": "1",
      "order": 2,
      "name": "Eröffnung der Sitzung\n- Feststellung der ordnungsgemäßen Ladung und der anwesenden Mitglieder\n- Feststellung der Beschlussfähigkeit\n",
      "created": "2016-11-03T14:14:26+01:00",
      "modified": "2016-11-03T14:14:26+01:00"
    },
    {
      "id": "https://nordstemmen.ratsinfomanagement.net/webservice/oparl/v1.1/body/1/agendaitem/13455",
      "type": "https://schema.oparl.org/1.1/AgendaItem",
      "number": "2",
      "order": 3,
      "name": "Verpflichtung und Pflichtenbelehrung durch die bisherige Ortsbürgermeisterin",
      "created": "2016-11-03T14:14:26+01:00",
      "modified": "2016-11-03T14:14:26+01:00"
    },
    {
      "id": "https://nordstemmen.ratsinfomanagement.net/webservice/oparl/v1.1/body/1/agendaitem/13462",
      "type": "https://schema.oparl.org/1.1/AgendaItem",
      "number": "3",
      "order": 4,
      "name": "Bekanntgabe der Bildung von Fraktionen und Gruppen",
      "created": "2016-11-03T14:16:21+01:00",
      "modified": "2016-11-03T14:16:21+01:00"
    },
    {
      "id": "https://nordstemmen.ratsinfomanagement.net/webservice/oparl/v1.1/body/1/agendaitem/13463",
      "type": "https://schema.oparl.org/1.1/AgendaItem",
      "number": "4",
      "order": 5,
      "name": "Wahl der Ortsbürgermeisterin/des Ortsbürgermeisters",
      "created": "2016-11-03T14:16:42+01:00",
      "modified": "2016-11-03T14:16:42+01:00"
    },
    {
      "id": "https://nordstemmen.ratsinfomanagement.net/webservice/oparl/v1.1/body/1/agendaitem/13464",
      "type": "https://schema.oparl.org/1.1/AgendaItem",
      "number": "5",
      "order": 6,
      "name": "Feststellung der Tagesordnung",
      "created": "2016-11-03T14:17:01+01:00",
      "modified": "2016-11-03T14:17:01+01:00"
    },
    {
      "id": "https://nordstemmen.ratsinfomanagement.net/webservice/oparl/v1.1/body/1/agendaitem/13465",
      "type": "https://schema.oparl.org/1.1/AgendaItem",
      "number": "6",
      "order": 7,
      "name": "Wahl von zwei gleichberechtigten stellvertretenden Ortsbürgermeisterinnen/Ortsbürgermeistern",
      "created": "2016-11-03T14:17:39+01:00",
      "modified": "2016-11-03T14:17:39+01:00"
    },
    {
      "id": "https://nordstemmen.ratsinfomanagement.net/webservice/oparl/v1.1/body/1/agendaitem/13466",
      "type": "https://schema.oparl.org/1.1/AgendaItem",
      "number": "7",
      "order": 8,
      "name": "Verabschiedung ausgeschiedener Ortsratsmitglieder",
      "created": "2016-11-03T14:18:01+01:00",
      "modified": "2016-11-03T14:18:01+01:00"
    },
    {
      "id": "https://nordstemmen.ratsinfomanagement.net/webservice/oparl/v1.1/body/1/agendaitem/13456",
      "type": "https://schema.oparl.org/1.1/AgendaItem",
      "number": "8",
      "order": 9,
      "name": "Einwohnerfragestunde",
      "created": "2016-11-03T14:14:26+01:00",
      "modified": "2016-11-03T14:14:26+01:00"
    },
    {
      "id": "https://nordstemmen.ratsinfomanagement.net/webservice/oparl/v1.1/body/1/agendaitem/13514",
      "type": "https://schema.oparl.org/1.1/AgendaItem",
      "number": "9",
      "order": 11,
      "name": "Fortführung der Bürgersprechstunde vor der Sitzung des Ortsrates\n- Beratung und Beschlussfassung",
      "created": "2016-11-04T08:56:13+01:00",
      "modified": "2016-11-04T08:56:13+01:00"
    },
    {
      "id": "https://nordstemmen.ratsinfomanagement.net/webservice/oparl/v1.1/body/1/agendaitem/13467",
      "type": "https://schema.oparl.org/1.1/AgendaItem",
      "number": "10",
      "order": 12,
      "name": "Benennung einer Vertreterin/eines Vertreters einschließlich Stellvertretung aus dem Ortsrat für folgende in der Ortschaft gelegene Einrichtungen bzw. bestehende Vereine und Verbände\n- für den Kindertagesstättenausschuss des Kindergartens in der Ortschaft Rössing\n- für den Vorstand im Verein Freizeitsee Rössing e. V.\n- für den Vorstand im Kulturkreis Rössing e. V.",
      "created": "2016-11-03T14:20:38+01:00",
      "modified": "2016-11-03T14:20:38+01:00"
    },
    {
      "id": "https://nordstemmen.ratsinfomanagement.net/webservice/oparl/v1.1/body/1/agendaitem/13468",
      "type": "https://schema.oparl.org/1.1/AgendaItem",
      "number": "11",
      "order": 13,
      "name": "Verwendung von im Haushaltsjahr 2016 noch zur Verfügung stehenden Ortsratsmitteln",
      "created": "2016-11-03T14:21:14+01:00",
      "modified": "2016-11-03T14:21:14+01:00"
    },
    {
      "id": "https://nordstemmen.ratsinfomanagement.net/webservice/oparl/v1.1/body/1/agendaitem/13457",
      "type": "https://schema.oparl.org/1.1/AgendaItem",
      "number": "12",
      "order": 14,
      "name": "Anhörung zum Haushaltsplan 2017 und zum Investitionsprogramm bis 2020 für die Ortschaft Rössing",
      "consultation": "https://nordstemmen.ratsinfomanagement.net/webservice/oparl/v1.1/body/1/consultation/3671",
      "created": "2016-11-03T14:14:26+01:00",
      "modified": "2016-11-03T14:14:26+01:00"
    },
    {
      "id": "https://nordstemmen.ratsinfomanagement.net/webservice/oparl/v1.1/body/1/agendaitem/13469",
      "type": "https://schema.oparl.org/1.1/AgendaItem",
      "number": "13",
      "order": 15,
      "name": "Neujahrsempfang 2017",
      "created": "2016-11-03T14:21:37+01:00",
      "modified": "2016-11-03T14:21:37+01:00"
    },
    {
      "id": "https://nordstemmen.ratsinfomanagement.net/webservice/oparl/v1.1/body/1/agendaitem/13470",
      "type": "https://schema.oparl.org/1.1/AgendaItem",
      "number": "14",
      "order": 16,
      "name": "Durchführung weiterer Veranstaltungstermine des Ortsrates im Jahr 2017",
      "created": "2016-11-03T14:22:14+01:00",
      "modified": "2016-11-03T14:22:14+01:00"
    },
    {
      "id": "https://nordstemmen.ratsinfomanagement.net/webservice/oparl/v1.1/body/1/agendaitem/13458",
      "type": "https://schema.oparl.org/1.1/AgendaItem",
      "number": "15",
      "order": 17,
      "name": "Mitteilungen des Bürgermeisters",
      "created": "2016-11-03T14:14:26+01:00",
      "modified": "2016-11-03T14:14:26+01:00"
    },
    {
      "id": "https://nordstemmen.ratsinfomanagement.net/webservice/oparl/v1.1/body/1/agendaitem/13459",
      "type": "https://schema.oparl.org/1.1/AgendaItem",
      "number": "16",
      "order": 18,
      "name": "Mitteilungen der Ortsbürgermeisterin/des Ortsbürgermeisters",
      "created": "2016-11-03T14:14:26+01:00",
      "modified": "2016-11-03T14:14:26+01:00"
    },
    {
      "id": "https://nordstemmen.ratsinfomanagement.net/webservice/oparl/v1.1/body/1/agendaitem/13460",
      "type": "https://schema.oparl.org/1.1/AgendaItem",
      "number": "17",
      "order": 19,
      "name": "Anträge und Anfragen",
      "created": "2016-11-03T14:14:26+01:00",
      "modified": "2016-11-03T14:14:26+01:00"
    }
  ]
}