{
  "id": "https://nordstemmen.ratsinfomanagement.net/webservice/oparl/v1.1/body/1/paper/529",
  "reference": "DS 56/2010",
  "name": "Bauantrag auf Errichtung eines Mobilfunkmastes in der Gemarkung Burgstemmen",
  "paperType": "Mitteilungsvorlage",
  "date": "2010-10-26",
  "mainFile": {
    "id": "https://nordstemmen.ratsinfomanagement.net/webservice/oparl/v1.1/body/1/file/1-5777",
    "type": "https://schema.oparl.org/1.1/File",
    "body": "https://nordstemmen.ratsinfomanagement.net/webservice/oparl/v1.1/body/1",
    "name": "Mitteilungsvorlage (Bauantrag auf Errichtung eines Mobilfunkmastes in der Gemarkung Burgstemmen)",
    "mimeType": "application/pdf",
    "date": "2010-10-26",
    "accessUrl": "https://nordstemmen.ratsinfomanagement.net/webservice/oparl/v1.1/body/1/files/UGhVM0hpd2NXNFdFcExjZccgv5VLdPd6cZJcOG3KH6TiHIj74pIJAtoy98xlz3DH/Mitteilungsvorlage_DS_56-2010.pdf",
    "downloadUrl": "https://nordstemmen.ratsinfomanagement.net/webservice/oparl/v1.1/body/1/files/download/UGhVM0hpd2NXNFdFcExjZccgv5VLdPd6cZJcOG3KH6TiHIj74pIJAtoy98xlz3DH/Mitteilungsvorlage_DS_56-2010.pdf",
    "created": "2010-10-18T13:26:47+02:00",
    "modified": "2010-10-18T13:26:47+02:00"
  },
  "consultation": [
    {
      "id": "https://nordstemmen.ratsinfomanagement.net/webservice/oparl/v1.1/body/1/consultation/1378",
      "type": "https://schema.oparl.org/1.1/Consultation",
      "meeting": "https://nordstemmen.ratsinfomanagement.net/webservice/oparl/v1.1/body/1/meeting/1531",
      "organization": [
        "https://nordstemmen.ratsinfomanagement.net/webservice/oparl/v1.1/body/1/organization/1-12"
      ],
      "created": "2010-10-11T09:50:53+02:00",
      "modified": "2010-10-11T09:50:53+02:00"
    }
  ]
}